{"Exif":{"Lat":0,"Long":0,"Date":"2024-04-16T16:15:11+02:00","Tags":{"ApertureValue":1.3561438092556088,"BitsPerSample":[8,8,8],"BrightnessValue":5.811328778385734,"ComponentsConfiguration":"","DateTimeDigitized|time.Time":"2024-04-16T16:15:11+02:00","DateTimeOriginal|time.Time":"2024-04-16T16:15:11+02:00","DateTime|time.Time":"2024-04-21T16:50:11+02:00","DigitalZoomRatio":1.356053811659193,"ExposureTime|*big.Rat":"1/130","FNumber":1.6,"FocalLength":4.2,"FocalLengthIn35mmFilm|int":"35","ISOSpeedRatings|int":"32","ImageLength|int":"2668","ImageWidth|int":"3123","LensMake":"Apple","LensModel":"iPhone 12 mini back dual wide camera 4.2mm f/1.6","Make":"Apple","Model":"iPhone 12 mini","Orientation|int":"1","PhotometricInterpretation|int":"2","PixelXDimension|int":"1772","PixelYDimension|int":"1772","SamplesPerPixel|int":"3","SceneCaptureType|int":"0","SceneType":"","ShutterSpeedValue":7.02280068402052,"Software":"Adobe Photoshop 24.7 (Macintosh)","SubSecTimeDigitized":"053","SubSecTimeOriginal":"053","SubjectArea":[2017,1511,2320,1395],"YCbCrPositioning|int":"1"}}}
